Metadata-Version: 1.0
Name: thirukuzhal
Version: 0.1
Summary: ThiruKuzhal Test in the world
Home-page: UNKNOWN
Author: Thirumoorthy
Author-email: thirumoorthy.gmk@gmail.com
License: Mepco
Platform: UNKNOWN
